netsurv/__init__.py
netsurv/codes.py
netsurv/dvrip.py
netsurv/tests/__init__.py
netsurv/tests/test_dvrip.py
netsurv-0.1.5.dist-info/DESCRIPTION.rst
netsurv-0.1.5.dist-info/METADATA
netsurv-0.1.5.dist-info/RECORD
netsurv-0.1.5.dist-info/WHEEL
netsurv-0.1.5.dist-info/metadata.json
netsurv-0.1.5.dist-info/top_level.txt
